{
  "$schema": "https://biomejs.dev/schemas/2.3.13/schema.json",
  "root": true,
  "vcs": {
    "enabled": true,
    "clientKind": "git",
    "useIgnoreFile": true
  },
  "files": {
    "ignoreUnknown": true,
    "includes": ["apps/**/*.{ts,tsx,js,jsx}", "packages/**/*.{ts,tsx,js,jsx}"]
  },
  "formatter": {
    "enabled": true,
    "indentStyle": "space",
    "indentWidth": 2,
    "lineWidth": 100
  },
  "linter": {
    "enabled": true,
    "rules": {
      "recommended": true,
      "suspicious": {
        "noUnknownAtRules": "off"
      },
      "style": {
        "noNonNullAssertion": "off"
      }
    }
  },
  "css": {
    "parser": {
      "cssModules": false,
      "allowWrongLineComments": false,
      "tailwindDirectives": true
    },
    "formatter": {
      "enabled": true,
      "quoteStyle": "double"
    }
  },
  "javascript": {
    "formatter": {
      "quoteStyle": "single",
      "semicolons": "always",
      "trailingCommas": "es5"
    }
  },
  "assist": {
    "enabled": true,
    "actions": {
      "source": {
        "organizeImports": "on"
      }
    }
  }
}
